green_ac/__init__.py
green_ac/_green_ac.cpython-311-x86_64-linux-gnu.so
green_ac-0.2.5.dist-info/RECORD
green_ac-0.2.5.dist-info/METADATA
green_ac-0.2.5.dist-info/WHEEL
green_ac-0.2.5.dist-info/licenses/LICENSE
green_ac.libs/libgmpxx-25f6cf8d.so.4.4.0
green_ac.libs/libgmp-afec2dd4.so.10.2.0
