Metadata-Version: 2.1
Name: green-ac
Version: 0.2.5
Summary: Analytical continuation suits for Green Software Package
Author-Email: Sergei Iskakov <siskakov@umich.edu>
Classifier: Development Status :: 5 - Production/Stable
Classifier: Programming Language :: Python :: 3
Classifier: License :: OSI Approved :: MIT License
Classifier: Operating System :: POSIX
Classifier: Operating System :: Unix
Classifier: Operating System :: MacOS
Project-URL: Homepage, https://green-phys.org
Project-URL: Issues, https://github.com/Green-Phys/green-ac/issues
Requires-Python: >=3.8
Requires-Dist: numpy
Requires-Dist: h5py
Requires-Dist: scipy
Requires-Dist: coverage>=5.0.3; extra == "tests"
Requires-Dist: pytest; extra == "tests"
Requires-Dist: pytest-benchmark[histogram]>=3.2.1; extra == "tests"
Provides-Extra: tests
